pyguppy_client_lib/NanoporeCommunityTCs28November2018.pdf
pyguppy_client_lib/THIRD_PARTY_LICENSES
pyguppy_client_lib/__init__.py
pyguppy_client_lib/client_lib.cpython-39-darwin.so
pyguppy_client_lib/example.py
pyguppy_client_lib/helper_functions.py
pyguppy_client_lib/libguppy_client.7.2.15.dylib
pyguppy_client_lib/libguppy_client.7.dylib
pyguppy_client_lib/libguppy_client.dylib
pyguppy_client_lib/pyclient.py
pyguppy_client_lib/test/__init__.py
pyguppy_client_lib/test/test_client.py
pyguppy_client_lib/test/test_conversion_utils.py
pyguppy_client_lib/test/test_pyclient.py
pyguppy_client_lib/test/data/dna/file0.fast5
pyguppy_client_lib/test/data/dna/file1.fast5
pyguppy_client_lib/test/data/dna/file2.fast5
pyguppy_client_lib/test/data/dna/file3.fast5
pyguppy_client_lib/test/data/dna/file4.fast5
pyguppy_client_lib/test/data/dna/file6.pod5
ont_pyguppy_client_lib-7.2.15.dist-info/METADATA
ont_pyguppy_client_lib-7.2.15.dist-info/WHEEL
ont_pyguppy_client_lib-7.2.15.dist-info/top_level.txt
ont_pyguppy_client_lib-7.2.15.dist-info/RECORD
