Metadata-Version: 2.1
Name: ont-pyguppy-client-lib
Version: 7.2.15
Summary: Python bindings for the GuppyClient library.
Home-page: http://www.nanoporetech.com
Author: Oxford Nanopore Technologies plc
Author-email: unknown@unknown.com
Classifier: Development Status :: 5 - Production/Stable
Classifier: Environment :: Console
Classifier: Intended Audience :: Developers
Classifier: Intended Audience :: Science/Research
Classifier: License :: Other/Proprietary License
Classifier: Natural Language :: English
Classifier: Operating System :: POSIX :: Linux
Classifier: Programming Language :: C++
Classifier: Programming Language :: Python :: 3 :: Only
Classifier: Topic :: Scientific/Engineering :: Bio-Informatics
Requires-Dist: numpy
